busylib/__init__.py
busylib/client.py
busylib/exceptions.py
busylib/types.py
busylib-0.2.0.dist-info/licenses/LICENSE
busylib-0.2.0.dist-info/METADATA
busylib-0.2.0.dist-info/WHEEL
busylib-0.2.0.dist-info/top_level.txt
busylib-0.2.0.dist-info/RECORD
