Metadata-Version: 2.4
Name: busylib
Version: 0.2.0
Summary: Python library for Busy Bar API
Author-email: flipperdevices <pypi@flipperdevices.com>
Project-URL: Homepage, https://github.com/busy-app/busylib-py
Project-URL: Repository, https://github.com/busy-app/busylib-py
Project-URL: Documentation, https://busylib.readthedocs.io
Classifier: Development Status :: 3 - Alpha
Classifier: Intended Audience :: Developers
Classifier: Programming Language :: Python :: 3
Classifier: Programming Language :: Python :: 3.10
Classifier: Programming Language :: Python :: 3.11
Classifier: Programming Language :: Python :: 3.12
Classifier: Programming Language :: Python :: 3.13
Requires-Python: >=3.10
License-File: LICENSE
Requires-Dist: requests==2.32.4
Provides-Extra: dev
Requires-Dist: pytest==8.4.1; extra == "dev"
Requires-Dist: requests-mock==1.12.1; extra == "dev"
Requires-Dist: ruff; extra == "dev"
Dynamic: license-file
